pnpm/__init__.py
pnpm/generate
pnpm/generator/__pkg__/.eslintrc.js
pnpm/generator/__pkg__/.gitattributes
pnpm/generator/__pkg__/.gitignore
pnpm/generator/__pkg__/.pnpm/config.yml
pnpm/generator/__pkg__/.pnpm/requirements.txt
pnpm/generator/__pkg__/.pnpm/scripts/build
pnpm/generator/__pkg__/.pnpm/scripts/dev
pnpm/generator/__pkg__/.pnpm/scripts/release
pnpm/generator/__pkg__/.pnpm/scripts/sass
pnpm/generator/__pkg__/.pnpm/scripts/script/__init__.py
pnpm/generator/__pkg__/.pnpm/scripts/script/config.py
pnpm/generator/__pkg__/.pnpm/scripts/script/script.py
pnpm/generator/__pkg__/.pnpm/scripts/server
pnpm/generator/__pkg__/.pnpm/scripts/test
pnpm/generator/__pkg__/.requirements.txt
pnpm/generator/__pkg__/README.md
pnpm/generator/__pkg__/__tests__/index.js
pnpm/generator/__pkg__/docs/__pkg___demo.js
pnpm/generator/__pkg__/docs/index.html
pnpm/generator/__pkg__/jest.config.js
pnpm/generator/__pkg__/package.json
pnpm/generator/__pkg__/rollup.config.js
pnpm/generator/__pkg__/src/.build_assets/index.js
pnpm/generator/__pkg__/src/icons/chemistry.svg
pnpm/generator/__pkg__/src/icons/dna.svg
pnpm/generator/__pkg__/src/icons/gamification.svg
pnpm/generator/__pkg__/src/icons/linux--alt.svg
pnpm/generator/__pkg__/src/icons/microscope.svg
pnpm/generator/__pkg__/src/icons/model.svg
pnpm/generator/__pkg__/src/icons/palm-tree.svg
pnpm/generator/__pkg__/src/icons/umbrella.svg
pnpm/generator/__pkg__/src/index.js
pnpm/generator/__pkg__/src/pragmas/index.js
pnpm/generator/__pkg__/src/styles/main.scss
pnpm/helpers.py
pnpm/install
pnpm/install.py
pnpm/pnpm
pnpm-1.0.14.dist-info/LICENSE
pnpm-1.0.14.dist-info/WHEEL
pnpm-1.0.14.dist-info/METADATA
pnpm-1.0.14.dist-info/RECORD
