Metadata-Version: 2.1
Name: pnpm
Version: 1.0.14
Summary: 
Author: robo-monk
Author-email: rrobomonk@gmail.com
Requires-Python: >=3.6,<4.0
Classifier: Programming Language :: Python :: 3
Classifier: Programming Language :: Python :: 3.6
Classifier: Programming Language :: Python :: 3.7
Classifier: Programming Language :: Python :: 3.8
Classifier: Programming Language :: Python :: 3.9
Requires-Dist: PyYAML (>=5.4.1,<6.0.0)
Requires-Dist: click (>=7.1.2,<8.0.0)
Requires-Dist: numpy (>=1.20.1,<2.0.0)
Requires-Dist: rglob (>=1.7,<2.0)
Requires-Dist: rich (>=9.13.0,<10.0.0)
